AISuperServer/__init__.py
AISuperServer/create_server.py
AISuperServer/inferenceapi.py
AISuperServer/localmodel.py
AISuperServer/server.py
AISuperServer/serverfastapi.py
AISuperServer/uvicorn_server.py
AISuperServer/waitress_server.py
aisuperserver-0.1.99.dist-info/METADATA
aisuperserver-0.1.99.dist-info/WHEEL
aisuperserver-0.1.99.dist-info/RECORD
